messages/__init__.py
zenoh_ros2_sdk/__init__.py
zenoh_ros2_sdk/_cache.py
zenoh_ros2_sdk/_repositories.py
zenoh_ros2_sdk/attachment.py
zenoh_ros2_sdk/entity.py
zenoh_ros2_sdk/keyexpr.py
zenoh_ros2_sdk/logger.py
zenoh_ros2_sdk/message_registry.py
zenoh_ros2_sdk/publisher.py
zenoh_ros2_sdk/qos.py
zenoh_ros2_sdk/service_client.py
zenoh_ros2_sdk/service_server.py
zenoh_ros2_sdk/session.py
zenoh_ros2_sdk/subscriber.py
zenoh_ros2_sdk/utils.py
zenoh_ros2_sdk-0.1.1.dist-info/licenses/LICENSE
zenoh_ros2_sdk-0.1.1.dist-info/METADATA
zenoh_ros2_sdk-0.1.1.dist-info/WHEEL
zenoh_ros2_sdk-0.1.1.dist-info/top_level.txt
zenoh_ros2_sdk-0.1.1.dist-info/RECORD
