Metadata-Version: 2.4
Name: zenoh-ros2-sdk
Version: 0.1.1
Summary: Python SDK for ROS 2 communication via Zenoh - Use ROS 2 without ROS 2 environment
Home-page: https://github.com/robotis-git/zenoh_ros2_sdk
Author: Woojin Wie
Author-email: Woojin Wie <wwj@robotis.com>
Maintainer-email: Woojin Wie <wwj@robotis.com>
License: Apache-2.0
Project-URL: Homepage, https://github.com/robotis-git/zenoh_ros2_sdk
Project-URL: Repository, https://github.com/robotis-git/zenoh_ros2_sdk
Project-URL: Issues, https://github.com/robotis-git/zenoh_ros2_sdk/issues
Project-URL: Documentation, https://github.com/robotis-git/zenoh_ros2_sdk#readme
Keywords: ros2,zenoh,robotics,sdk,middleware
Classifier: Development Status :: 3 - Alpha
Classifier: Intended Audience :: Developers
Classifier: Topic :: Software Development :: Libraries :: Python Modules
Classifier: Topic :: Scientific/Engineering
Classifier: License :: OSI Approved :: Apache Software License
Classifier: Programming Language :: Python :: 3
Classifier: Programming Language :: Python :: 3.8
Classifier: Programming Language :: Python :: 3.9
Classifier: Programming Language :: Python :: 3.10
Classifier: Programming Language :: Python :: 3.11
Requires-Python: >=3.8
License-File: LICENSE
Requires-Dist: eclipse-zenoh>=0.10.0
Requires-Dist: rosbags>=0.11.0
Requires-Dist: GitPython>=3.1.18
Requires-Dist: tqdm>=4.64.0
Requires-Dist: json5>=0.9.0
Provides-Extra: dev
Requires-Dist: pytest>=7.0.0; extra == "dev"
Requires-Dist: pytest-cov>=4.0.0; extra == "dev"
Requires-Dist: black>=22.0.0; extra == "dev"
Requires-Dist: flake8>=4.0.0; extra == "dev"
Provides-Extra: docs
Requires-Dist: mkdocs>=1.5.0; extra == "docs"
Requires-Dist: mkdocs-material>=9.0.0; extra == "docs"
Requires-Dist: mkdocstrings[python]>=0.24.0; extra == "docs"
Requires-Dist: pymdown-extensions>=10.0; extra == "docs"
Dynamic: author
Dynamic: home-page
Dynamic: license-file
Dynamic: requires-python
